Metadata-Version: 1.2
Name: fileheaderPy
Version: 6.0.0
Summary: A way to create script python with beatiful header
Home-page: https://github.com/batestin1/
Author: Maycon Cypriano Batestin
Author-email: mayconcipriano@gmail.com
License: UNKNOWN
Project-URL: Código fonte, https://github.com/batestin1/
Project-URL: Download, https://github.com/batestin1/
Keywords: A way to create script python with beatiful header
Platform: UNKNOWN
